{
  "name": "@abstractions/type-checker",
  "version": "0.1.0",
  "exports": "./lib/mod.ts",
  "tasks": {
    "setup": "./scripts/setup-target.sh",
    "check": "deno check lib/mod.ts",
    "test": "deno test lib/",
    "jupyter": "cd notebooks && jupyter notebook --no-browser"
  },
  "imports": {
    "@std/fs": "jsr:@std/fs@^1.0.0",
    "@std/path": "jsr:@std/path@^1.0.0",
    "@std/assert": "jsr:@std/assert@^1.0.0",
    "@std/cli": "jsr:@std/cli@^1.0.0",
    "npm:typescript@5.3.3": "npm:typescript@5.3.3"
  },
  "nodeModulesDir": "auto",
  "compilerOptions": {
    "strict": true
  }
}
